{"matchPosition": "F", "matchShirtNumber": 10, "captain": false, "playerId": 0, "info": {"position": "F", "shirtNum": 10, "positionInfo": "Centre Striker"}, "nationalTeam": {"isoCode": "GB-ENG", "country": "England", "demonym": "English"}, "birth": {"date": {"millis": 837216000000, "label": "13 July 1996"}, "country": {"isoCode": "GB-ENG", "country": "England", "demonym": "English"}}, "age": "23 years 28 days", "name": {"display": "Che Adams", "first": "Che", "last": "Adams"}, "id": 10905, "altIds": {"opta": "p200439"}, "topStats": {"Appearances": "22", "Goals": "0", "Wins": "8", "Losses": "12"}, "skills": {"Attack": {"Goals": "0", "Goals per match": "22", "Headed goals": "0", "Goals with right foot": "0", "Goals with left foot": "0", "Penalties scored": "0", "Freekicks scored": "0", "Shots": "18", "Shots on target": "2", "Shooting accuracy %": "11%", "Hit woodwork": "1", "Big chances missed": "6"}, "Team Play": {"Assists": "2", "Passes": "163", "Passes per match": "7.41", "Big chances created": "4", "Crosses": "8", "Cross accuracy %": "13%", "Through balls": "2", "Accurate long balls": "2"}, "Discipline": {"Yellow cards": "0", "Red cards": "0", "Fouls": "13", "Offsides": "7"}, "Defence": {"Tackles": "2", "Tackle success %": "2%", "Blocked shots": "8", "Interceptions": "2", "Clearances": "7", "Headed Clearance": "3", "Recoveries": "39", "Duels won": "45", "Duels lost": "83", "Successful 50/50s": "10", "Aerial battles won": "27", "Aerial battles lost": "48", "Errors leading to goal": "0"}}}