{"matchPosition": "F", "matchShirtNumber": 99, "captain": false, "playerId": 0, "info": {"position": "F", "positionInfo": "Forward"}, "nationalTeam": {"isoCode": "FR", "country": "France", "demonym": "French"}, "birth": {"date": {"millis": 137376000000, "label": "10 May 1974"}, "country": {"isoCode": "FR", "country": "France", "demonym": "French"}}, "age": "26 years 122 days", "name": {"display": "Sylvain Wiltord", "first": "Sylvain", "last": "Wiltord"}, "id": 1836, "altIds": {"opta": "p3887"}, "topStats": {"Appearances": "106", "Goals": "31", "Wins": "63", "Losses": "14"}, "skills": {"Attack": {"Goals": "31", "Goals per match": "0.29", "Headed goals": "0", "Goals with right foot": "0", "Goals with left foot": "1", "Penalties scored": "0", "Freekicks scored": "0", "Shots": "3", "Shots on target": "1", "Shooting accuracy %": "33%", "Hit woodwork": "0", "Big chances missed": "0"}, "Team Play": {"Assists": "16", "Passes": "34", "Passes per match": "0.32", "Big chances created": "0", "Crosses": "5"}, "Discipline": {"Yellow cards": "1", "Red cards": "0", "Fouls": "0", "Offsides": "0"}, "Defence": {"Tackles": "1", "Blocked shots": "1", "Interceptions": "0", "Clearances": "0", "Headed Clearance": "0"}}}