{"matchPosition": "D", "matchShirtNumber": 20, "captain": false, "playerId": 0, "info": {"position": "D", "shirtNum": 20, "positionInfo": "Centre Central Defender"}, "nationalTeam": {"isoCode": "FR", "country": "France", "demonym": "French"}, "birth": {"date": {"millis": 624067200000, "label": "11 October 1989"}, "country": {"isoCode": "FR", "country": "France", "demonym": "French"}}, "age": "28 years 304 days", "name": {"display": "Maxime Le Marchand", "first": "Maxime", "last": "Le Marchand"}, "id": 20503, "altIds": {"opta": "p61739"}, "topStats": {"Appearances": "26", "Goals": "0", "Wins": "7", "Losses": "17"}, "skills": {"Defence": {"Clean sheets": "3", "Goals conceded": "53", "Tackles": "56", "Tackle success %": "64%", "Last man tackles": "0", "Blocked shots": "3", "Interceptions": "54", "Clearances": "122", "Headed Clearance": "48", "Clearances off line": "0", "Recoveries": "164", "Duels won": "129", "Duels lost": "106", "Successful 50/50s": "10", "Aerial battles won": "56", "Aerial battles lost": "45", "Own goals": "0", "Errors leading to goal": "1"}, "Team Play": {"Assists": "1", "Passes": "1,386", "Passes per match": "53.31", "Big chances created": "1", "Crosses": "17", "Cross accuracy %": "24%", "Through balls": "1", "Accurate long balls": "91"}, "Discipline": {"Yellow cards": "5", "Red cards": "0", "Fouls": "28", "Offsides": "3"}, "Attack": {"Goals": "0", "Headed goals": "0", "Goals with right foot": "0", "Goals with left foot": "0", "Hit woodwork": "0"}}}