{"matchPosition": "F", "matchShirtNumber": 20, "captain": false, "playerId": 0, "info": {"position": "F", "shirtNum": 20, "positionInfo": "Forward"}, "nationalTeam": {"isoCode": "IE", "country": "Ireland", "demonym": "Irish"}, "birth": {"date": {"millis": 404438400000, "label": "26 October 1982"}, "country": {"isoCode": "GB-ENG", "country": "England", "demonym": "English"}, "place": "Leeds"}, "age": "24 years 96 days", "name": {"display": "Caleb Folan", "first": "Caleb", "middle": "Colman", "last": "Folan"}, "id": 2101, "altIds": {"opta": "p11607"}, "topStats": {"Appearances": "38", "Goals": "5", "Wins": "9", "Losses": "19"}, "skills": {"Attack": {"Goals": "5", "Goals per match": "0.13", "Headed goals": "1", "Goals with right foot": "3", "Goals with left foot": "1", "Penalties scored": "0", "Freekicks scored": "0", "Shots": "25", "Shots on target": "11", "Shooting accuracy %": "44%", "Hit woodwork": "1", "Big chances missed": "0"}, "Team Play": {"Assists": "0", "Passes": "519", "Passes per match": "13.66", "Big chances created": "0", "Crosses": "21"}, "Discipline": {"Yellow cards": "4", "Red cards": "1", "Fouls": "50", "Offsides": "27"}, "Defence": {"Tackles": "22", "Blocked shots": "3", "Interceptions": "6", "Clearances": "9", "Headed Clearance": "1"}}}