{"matchPosition": "F", "matchShirtNumber": 10, "captain": false, "playerId": 0, "info": {"position": "M", "shirtNum": 10, "positionInfo": "Midfielder", "loan": true}, "nationalTeam": {"isoCode": "PL", "country": "Poland", "demonym": "Polish"}, "birth": {"date": {"millis": 347846400000, "label": "9 January 1981"}, "country": {"isoCode": "PL", "country": "Poland", "demonym": "Polish"}}, "age": "27 years 255 days", "name": {"display": "Ebi Smolarek", "first": "Ebi", "last": "Smolarek"}, "id": 3582, "altIds": {"opta": "p7522"}, "topStats": {"Appearances": "12", "Goals": "0", "Wins": "4", "Losses": "7"}, "skills": {"Attack": {"Goals": "0", "Goals per match": "12", "Headed goals": "0", "Goals with right foot": "0", "Goals with left foot": "0", "Penalties scored": "0", "Freekicks scored": "0", "Shots": "5", "Shots on target": "1", "Shooting accuracy %": "20%", "Hit woodwork": "0", "Big chances missed": "0"}, "Team Play": {"Assists": "0", "Passes": "53", "Passes per match": "4.42", "Big chances created": "0", "Crosses": "0", "Cross accuracy %": "0%", "Through balls": "1", "Accurate long balls": "1"}, "Discipline": {"Yellow cards": "1", "Red cards": "0", "Fouls": "6", "Offsides": "4"}, "Defence": {"Tackles": "6", "Tackle success %": "50%", "Blocked shots": "1", "Interceptions": "3", "Clearances": "1", "Headed Clearance": "1", "Recoveries": "5", "Duels won": "10", "Duels lost": "22", "Successful 50/50s": "1", "Aerial battles won": "1", "Aerial battles lost": "4", "Errors leading to goal": "0"}}}