{"matchPosition": "M", "matchShirtNumber": 25, "captain": false, "playerId": 0, "info": {"position": "M", "shirtNum": 25, "positionInfo": "Centre Attacking Midfielder"}, "nationalTeam": {"isoCode": "BE", "country": "Belgium", "demonym": "Belgian"}, "birth": {"date": {"millis": 564537600000, "label": "22 November 1987"}, "country": {"isoCode": "BE", "country": "Belgium", "demonym": "Belgian"}, "place": "Brussels"}, "age": "20 years 297 days", "name": {"display": "Marouane Fellaini", "first": "Marouane", "last": "Fellaini"}, "id": 3604, "altIds": {"opta": "p41184"}, "topStats": {"Appearances": "260", "Goals": "37", "Wins": "115", "Losses": "65"}, "skills": {"Attack": {"Goals": "37", "Goals per match": "0.14", "Headed goals": "15", "Goals with right foot": "19", "Goals with left foot": "3", "Penalties scored": "0", "Freekicks scored": "0", "Shots": "387", "Shots on target": "147", "Shooting accuracy %": "38%", "Hit woodwork": "13", "Big chances missed": "37"}, "Team Play": {"Assists": "16", "Passes": "11,297", "Passes per match": "43.45", "Big chances created": "17", "Crosses": "155", "Cross accuracy %": "21%", "Through balls": "36", "Accurate long balls": "405"}, "Discipline": {"Yellow cards": "55", "Red cards": "3", "Fouls": "588", "Offsides": "89"}, "Defence": {"Tackles": "622", "Tackle success %": "77%", "Blocked shots": "98", "Interceptions": "336", "Clearances": "594", "Headed Clearance": "274", "Recoveries": "1,477", "Duels won": "1,899", "Duels lost": "1,873", "Successful 50/50s": "124", "Aerial battles won": "895", "Aerial battles lost": "562", "Errors leading to goal": "1"}}}