{"matchPosition": "M", "matchShirtNumber": 34, "captain": false, "playerId": 0, "info": {"position": "M", "shirtNum": 26, "positionInfo": "Centre Central Midfielder"}, "nationalTeam": {"isoCode": "ZA", "country": "South Africa", "demonym": "South African"}, "birth": {"date": {"millis": 470102400000, "label": "24 November 1984"}, "country": {"isoCode": "ZA", "country": "South Africa", "demonym": "South African"}}, "age": "24 years 314 days", "name": {"display": "Kagisho Dikgacoi", "first": "Kagisho", "last": "Dikgacoi"}, "id": 3887, "altIds": {"opta": "p46967"}, "topStats": {"Appearances": "39", "Goals": "0", "Wins": "14", "Losses": "15"}, "skills": {"Attack": {"Goals": "0", "Goals per match": "39", "Headed goals": "0", "Goals with right foot": "0", "Goals with left foot": "0", "Penalties scored": "0", "Freekicks scored": "0", "Shots": "25", "Shots on target": "7", "Shooting accuracy %": "28%", "Hit woodwork": "0", "Big chances missed": "4"}, "Team Play": {"Assists": "0", "Passes": "1,120", "Passes per match": "28.72", "Big chances created": "0", "Crosses": "16", "Cross accuracy %": "6%", "Through balls": "9", "Accurate long balls": "73"}, "Discipline": {"Yellow cards": "4", "Red cards": "2", "Fouls": "26", "Offsides": "0"}, "Defence": {"Tackles": "54", "Tackle success %": "70%", "Blocked shots": "6", "Interceptions": "49", "Clearances": "50", "Headed Clearance": "21", "Recoveries": "182", "Duels won": "126", "Duels lost": "153", "Successful 50/50s": "12", "Aerial battles won": "45", "Aerial battles lost": "67", "Errors leading to goal": "0"}}}