{"matchPosition": "F", "matchShirtNumber": 43, "captain": false, "playerId": 0, "info": {"position": "F", "shirtNum": 43, "positionInfo": "Centre Striker"}, "nationalTeam": {"isoCode": "SE", "country": "Sweden", "demonym": "Swedish"}, "birth": {"date": {"millis": 793411200000, "label": "22 February 1995"}, "country": {"isoCode": "SE", "country": "Sweden", "demonym": "Swedish"}, "place": "Tingstad"}, "age": "18 years 352 days", "name": {"display": "Muamer Tankovic", "first": "Muamer", "last": "Tankovic"}, "id": 4310, "altIds": {"opta": "p102046"}, "topStats": {"Appearances": "3", "Goals": "0", "Wins": "0", "Losses": "2"}, "skills": {"Attack": {"Goals": "0", "Goals per match": "3", "Headed goals": "0", "Goals with right foot": "0", "Goals with left foot": "0", "Penalties scored": "0", "Freekicks scored": "0", "Shots": "1", "Shots on target": "0", "Shooting accuracy %": "1%", "Hit woodwork": "0", "Big chances missed": "0"}, "Team Play": {"Assists": "0", "Passes": "13", "Passes per match": "4.33", "Big chances created": "1", "Crosses": "0"}, "Discipline": {"Yellow cards": "0", "Red cards": "0", "Fouls": "1", "Offsides": "0"}, "Defence": {"Tackles": "0", "Blocked shots": "0", "Interceptions": "0", "Clearances": "1", "Headed Clearance": "1"}}}