{"matchPosition": "G", "matchShirtNumber": 33, "captain": false, "playerId": 0, "info": {"position": "G", "shirtNum": 33, "positionInfo": "Goalkeeper"}, "nationalTeam": {"isoCode": "BR", "country": "Brazil", "demonym": "Brazilian"}, "birth": {"date": {"millis": 305164800000, "label": "3 September 1979"}, "country": {"isoCode": "BR", "country": "Brazil", "demonym": "Brazilian"}, "place": "Duque de Caxias"}, "age": "33 years 12 days", "name": {"display": "Julio César", "first": "Julio Cesar", "last": "Soares de Espindola"}, "id": 4566, "altIds": {"opta": "p19928"}, "topStats": {"Appearances": "24", "Clean sheets": "5", "Wins": "2", "Losses": "13"}, "skills": {"Goalkeeping": {"Saves": "97", "Penalties saved": "0", "Punches": "23", "High Claims": "23", "Catches": "13", "Sweeper clearances": "5", "Throw outs": "83", "Goal Kicks": "237"}, "Defence": {"Clean sheets": "5", "Goals conceded": "37", "Errors leading to goal": "3", "Own goals": "1"}, "Discipline": {"Yellow cards": "0", "Red cards": "0", "Fouls": "0"}, "Team Play": {"Goals": "0", "Assists": "0", "Passes": "364", "Passes per match": "15.17", "Accurate long balls": "79"}}}