{"matchPosition": "M", "matchShirtNumber": 12, "captain": false, "playerId": 0, "info": {"position": "M", "shirtNum": 12, "positionInfo": "Centre Defensive Midfielder"}, "nationalTeam": {"isoCode": "KE", "country": "Kenya", "demonym": "Kenyan"}, "birth": {"date": {"millis": 677808000000, "label": "25 June 1991"}, "country": {"isoCode": "KE", "country": "Kenya", "demonym": "Kenyan"}, "place": "Nairobi"}, "age": "22 years 53 days", "name": {"display": "Victor Wanyama", "first": "Victor", "last": "Wanyama"}, "id": 4816, "altIds": {"opta": "p54756"}, "topStats": {"Appearances": "154", "Goals": "10", "Wins": "83", "Losses": "38"}, "skills": {"Attack": {"Goals": "10", "Goals per match": "0.06", "Headed goals": "3", "Goals with right foot": "6", "Goals with left foot": "1", "Penalties scored": "0", "Freekicks scored": "0", "Shots": "136", "Shots on target": "33", "Shooting accuracy %": "24%", "Hit woodwork": "1", "Big chances missed": "4"}, "Team Play": {"Assists": "3", "Passes": "6,899", "Passes per match": "44.8", "Big chances created": "5", "Crosses": "42", "Cross accuracy %": "10%", "Through balls": "6", "Accurate long balls": "381"}, "Discipline": {"Yellow cards": "36", "Red cards": "3", "Fouls": "255", "Offsides": "1"}, "Defence": {"Tackles": "385", "Tackle success %": "77%", "Blocked shots": "31", "Interceptions": "217", "Clearances": "260", "Headed Clearance": "134", "Recoveries": "980", "Duels won": "953", "Duels lost": "852", "Successful 50/50s": "152", "Aerial battles won": "281", "Aerial battles lost": "265", "Errors leading to goal": "4"}}}